gmx_pes/__init__.py
gmx_pes/gmx_pes.py
gmx_pes-0.0.1a1.dist-info/DESCRIPTION.rst
gmx_pes-0.0.1a1.dist-info/METADATA
gmx_pes-0.0.1a1.dist-info/RECORD
gmx_pes-0.0.1a1.dist-info/WHEEL
gmx_pes-0.0.1a1.dist-info/metadata.json
gmx_pes-0.0.1a1.dist-info/top_level.txt
